<?xml version="1.0"?>
<extensions>
	
	<details>
		<title lang="EN">bpa's Squeezecenter Plugins Short</title>
	</details>
	
	<plugins>
		
		<plugin name="BBCiPlayerExtra" version="1.9.3" minTarget="7.3" maxTarget="7.*">
			<title lang="EN">BBCiPlayerExtra</title>
			<desc  lang="EN">BBCiPlayer Extra which provides access to all iPlayer radio programs by station, categories and schedules.</desc>
			<creator>bpa</creator>
			<email>baltontwo@eircom.net</email>
			<url>http://downloads.sourceforge.net/project/bpaplugins/BBCiPlayerExtra-v109_3.ZIP</url>
			<sha>5867c1f592ac0ca0ee550a0ea046f1ba1232fcfb</sha>
		</plugin>
	        <plugin name="BBCiPlayer" version="1.4.4" minTarget="7.4" maxTarget="*">
        		<title lang="EN">BBCiPlayer - DASH test version</title>
        		<desc  lang="EN">Listen to BBC iPlayer Live and Listen Again Radio streams.  Supports the highest quality streams available from the BBC for your location.  Users outside the UK are now able to receive restricted bitrate versions of all of the content available to UK users.  This includes listen again recordings of the last 7 days of BBC National, Regional and Local Radio from the UK.  DASH support added by bpa</desc>
        		<creator>Triode</creator>
        		<email>baltontwo@eircom.com</email>
        		<url>http://downloads.sourceforge.net/project/bpaplugins/BBCiPlayer-V1_4_4.ZIP</url>
        		<sha>307d989233247abdee51b5bbdda3b4c3aedde697</sha>
        	</plugin>
		

	</plugins>
	
</extensions>

